okta_graph/README.md
okta_graph/__init__.py
okta_graph/api.py
okta_graph/cache.py
okta_graph/graph.py
okta_graph/install.sh
okta_graph/logging.py
okta_graph/models.py
okta_graph/plugins.py
okta_graph/rule_parser.py
okta_graph/static/css/jsoneditor.css
okta_graph/static/css/main.css
okta_graph/static/icons/aws.png
okta_graph/static/icons/group.png
okta_graph/static/icons/manual_group.png
okta_graph/static/icons/rule.png
okta_graph/static/icons/user.png
okta_graph/static/img/jsoneditor-icons.svg
okta_graph/static/index.html
okta_graph/static/js/graph.js
okta_graph/static/js/jsoneditor.js
okta_graph/static/js/profile-editor.js
okta_graph-0.2.3.dist-info/METADATA
okta_graph-0.2.3.dist-info/WHEEL
okta_graph-0.2.3.dist-info/RECORD
