Metadata-Version: 2.3
Name: okta-graph
Version: 0.2.3
Summary: An ASGI web application that provides tools for graphing uset groups based on user attributes and group rules in Okta.
Author: Mathew Moon
Author-email: <me@mathewmoon.net>
Requires-Python: >=3.11
Classifier: Programming Language :: Python :: 3
Classifier: Programming Language :: Python :: 3.11
Classifier: Programming Language :: Python :: 3.12
Classifier: Programming Language :: Python :: 3.13
Requires-Dist: fastapi (>=0.109.2,<0.110.0)
Requires-Dist: loguru (>=0.7.2,<0.8.0)
Requires-Dist: okta (>=2.9.5,<2.10.0)
Requires-Dist: okta-expression-parser (>=0.4.0,<0.5.0)
Requires-Dist: pydantic (>=2.10.0,<2.11.0)
Requires-Dist: pydot (>=2.0.0,<2.1.0)
Requires-Dist: uvicorn (>=0.27.0,<0.28.0)
